GLU/__init__.py
GLU/create_location_report.py
GLU/filestatus.py
GLU/geostrip.py
GLU/geotag.py
GLU/geotag_report.py
GLU/home.py
GLU/location_filter.py
GLU/location_parse.py
GLU/location_report.py
GLU/main.py
GLU/mapMe.py
GLU/read_report.py
GLU/settings_loader.py
GoogleLocationUtility-0.1.0a1.dist-info/LICENSE
GoogleLocationUtility-0.1.0a1.dist-info/METADATA
GoogleLocationUtility-0.1.0a1.dist-info/WHEEL
GoogleLocationUtility-0.1.0a1.dist-info/entry_points.txt
GoogleLocationUtility-0.1.0a1.dist-info/top_level.txt
GoogleLocationUtility-0.1.0a1.dist-info/RECORD
