Metadata-Version: 2.1
Name: GoogleLocationUtility
Version: 0.1.0a1
Summary: Utility for Location History data from Google Takeout.
Home-page: https://github.com/NBPub/GoogleLocationUtility
Download-URL: https://github.com/NBPub/GoogleLocationUtility/archive/refs/heads/main.zip
Author: NBPub
License: GNU General Public License v3 (GPLv3)
Project-URL: Bug Tracker, https://github.com/GoogleLocationUtility/issues
Classifier: Programming Language :: Python :: 3
Classifier: License :: OSI Approved :: GNU General Public License v3 (GPLv3)
Classifier: Operating System :: OS Independent
Classifier: Topic :: Software Development :: Libraries :: Python Modules
Requires-Python: >=3.8
License-File: LICENSE
Requires-Dist: Click (>=8.0)
Requires-Dist: exif (>=1.3)
Requires-Dist: plotly (>=5.6)
Requires-Dist: pandas (>=1.4)
Requires-Dist: numpy (>=1.22)
Requires-Dist: matplotlib (>=3.5)
Requires-Dist: seaborn (>=0.11.2)
Requires-Dist: fastparquet (>=0.8)
Requires-Dist: Jinja2 (>=3.0)
